{
  "authorLabel": "",
  "commentLabel": "",
  "timestampLabel": "",
  "reactionsLabel": "",
  "postLocationLabel": "",
  "postLabelsLabel": "",
  "disableGooglePlusShare": true,
  "showAuthor": false,
  "showAuthorProfile": false,
  "showBacklinks": false,
  "showCommentLink": false,
  "showDateHeader": false,
  "showInlineAds": false,
  "showLabels": false,
  "showLocation": false,
  "showReactions": false,
  "showShareButtons": false,
  "showTimestamp": false,
  "postsPerAd": 1,
  "style": {
    "layout": "1x1",
    "unittype": "TextAndImage",
    "bgcolor": "#ffffff",
    "bordercolor": "#ffffff",
    "urlcolor": "#008000",
    "linkcolor": "#0000ff",
    "textcolor": "#000000"
  },
  "backlinksLabel": ""
}
